engine
players
