Metadata-Version: 1.1
Name: ultimate-ttt
Version: 1.4
Summary: Game engine and sample player for Ultimate TicTacToe games
Home-page: https://github.com/socialgorithm/ultimate-ttt-py
Author: socialgorithm
Author-email: hello@socialgorithm.org
License: UNKNOWN
Download-URL: https://github.com/socialgorithm/ultimate-ttt-py/archive/1.4.tar.gz
Keywords: ultimate tictactoe uttt ultimate-ttt
Platform: UNKNOWN
